setup.cfg
setup.py
Manifold.egg-info/PKG-INFO
Manifold.egg-info/SOURCES.txt
Manifold.egg-info/dependency_links.txt
Manifold.egg-info/entry_points.txt
Manifold.egg-info/requires.txt
Manifold.egg-info/top_level.txt
Manifold.egg-info/zip-safe
manifold/__init__.py
manifold/manifold.py